ameren_api/__init__.py
ameren_api/ameren.py
ameren_api/ameren_client.py
ameren_api/errors/__init__.py
ameren_api/errors/ameren_error.py
ameren_api-0.0.3.dist-info/METADATA
ameren_api-0.0.3.dist-info/WHEEL
ameren_api-0.0.3.dist-info/top_level.txt
ameren_api-0.0.3.dist-info/RECORD
