Metadata-Version: 2.1
Name: ameren-api
Version: 0.0.3
Summary: A small async API wrapper for Ameren.
Home-page: https://github.com/schwartzpub/ameren_api
Author: Jacob Schwartz
Author-email: Jacob Schwartz <jake@schwartzpub.com>
Project-URL: Homepage, https://github.com/schwartzpub/ameren_api
Project-URL: Bug Tracker, https://github.com/schwartzpub/ameren_api/issues
Classifier: Programming Language :: Python :: 3
Classifier: License :: OSI Approved :: MIT License
Classifier: Operating System :: OS Independent
Requires-Python: >=3.9
Requires-Dist: aiohttp
Requires-Dist: pydantic
Requires-Dist: beautifulsoup4
